[
null,
{"id":1,"members":[{"enemyId":60,"x":29,"y":319,"hidden":false},{"enemyId":60,"x":141,"y":301,"hidden":false},{"enemyId":60,"x":264,"y":298,"hidden":false},{"enemyId":60,"x":385,"y":319,"hidden":false},{"enemyId":60,"x":290,"y":373,"hidden":false},{"enemyId":60,"x":189,"y":364,"hidden":false},{"enemyId":60,"x":99,"y":382,"hidden":false},{"enemyId":60,"x":211,"y":444,"hidden":false}],"name":"Slime Encounter","pages":[{"conditions":{"actorHp":50,"actorId":1,"actorValid":false,"enemyHp":50,"enemyIndex":0,"enemyValid":false,"switchId":1,"switchValid":false,"turnA":0,"turnB":0,"turnEnding":false,"turnValid":false},"list":[{"code":0,"indent":0,"parameters":[]}],"span":0}]},
{"id":2,"members":[{"enemyId":2,"x":231,"y":343,"hidden":false},{"enemyId":3,"x":153,"y":379,"hidden":false},{"enemyId":4,"x":111,"y":412,"hidden":false},{"enemyId":1,"x":261,"y":310,"hidden":false}],"name":"Dopplegangers?","pages":[{"conditions":{"actorHp":50,"actorId":1,"actorValid":false,"enemyHp":50,"enemyIndex":0,"enemyValid":false,"switchId":1,"switchValid":false,"turnA":0,"turnB":0,"turnEnding":false,"turnValid":true},"list":[{"code":0,"indent":0,"parameters":[]}],"span":0}]},
{"id":3,"members":[{"enemyId":2,"x":228,"y":343,"hidden":false}],"name":"A bunch of fruity skeletons","pages":[{"conditions":{"actorHp":50,"actorId":1,"actorValid":false,"enemyHp":50,"enemyIndex":0,"enemyValid":false,"switchId":1,"switchValid":false,"turnA":0,"turnB":0,"turnEnding":false,"turnValid":false},"list":[{"code":0,"indent":0,"parameters":[]}],"span":0}]},
{"id":4,"members":[{"enemyId":2,"x":240,"y":349,"hidden":false}],"name":"Store shenanigans","pages":[{"conditions":{"actorHp":50,"actorId":1,"actorValid":false,"enemyHp":50,"enemyIndex":0,"enemyValid":false,"switchId":1,"switchValid":false,"turnA":0,"turnB":0,"turnEnding":false,"turnValid":false},"list":[{"code":0,"indent":0,"parameters":[]}],"span":0}]},
{"id":5,"members":[{"enemyId":2,"x":110,"y":427,"hidden":false},{"enemyId":3,"x":213,"y":382,"hidden":false},{"enemyId":4,"x":340,"y":337,"hidden":false}],"name":"Oh no","pages":[{"conditions":{"actorHp":50,"actorId":1,"actorValid":false,"enemyHp":50,"enemyIndex":0,"enemyValid":false,"switchId":1,"switchValid":false,"turnA":0,"turnB":0,"turnEnding":false,"turnValid":false},"list":[{"code":0,"indent":0,"parameters":[]}],"span":0}]}
]